sierra_ils_utils/__init__.py
sierra_ils_utils/py.typed
sierra_ils_utils/sierra_datetime.py
sierra_ils_utils/sierra_rest_client.py
sierra_ils_utils/utils.py
sierra_ils_utils-0.1.0.dist-info/METADATA
sierra_ils_utils-0.1.0.dist-info/WHEEL
sierra_ils_utils-0.1.0.dist-info/licenses/LICENSE
sierra_ils_utils-0.1.0.dist-info/RECORD
