Metadata-Version: 2.4
Name: sierra-ils-utils
Version: 0.1.0
Summary: A wrapper around httpx for working with the Sierra ILS REST API
Project-URL: Homepage, https://github.com/chimpy-me/sierra-ils-utils/
Project-URL: Repository, https://github.com/chimpy-me/sierra-ils-utils/
Author-email: Ray Voelker <ray.voelker@gmail.com>
License-Expression: MIT
License-File: LICENSE
Requires-Python: >=3.10
Requires-Dist: httpx<0.29.0,>=0.28.1
Provides-Extra: dev
Requires-Dist: pymarc<6.0.0,>=5.2.3; extra == 'dev'
Requires-Dist: pytest-asyncio>=0.25.0; extra == 'dev'
Requires-Dist: pytest>=8.3.4; extra == 'dev'
Requires-Dist: respx>=0.22.0; extra == 'dev'
Provides-Extra: marc
Requires-Dist: pymarc<6.0.0,>=5.2.3; extra == 'marc'
Provides-Extra: test
Requires-Dist: pytest-asyncio>=0.25.0; extra == 'test'
Requires-Dist: pytest>=8.3.4; extra == 'test'
Requires-Dist: respx>=0.22.0; extra == 'test'
